cmd_manager/__init__.py
cmd_manager/argument.py
cmd_manager/command.py
cmd_manager/management.py
cmd_manager-0.1.0.dist-info/LICENSE
cmd_manager-0.1.0.dist-info/METADATA
cmd_manager-0.1.0.dist-info/WHEEL
cmd_manager-0.1.0.dist-info/RECORD
