Metadata-Version: 2.1
Name: cmd-manager
Version: 0.1.0
Summary: A management command system for FastAPI and Flask inspired by Django management commands.
Home-page: https://github.com/mhsiddiqui/cmd-manager
License: MIT
Keywords: fastapi,flask,starlette,management-commands
Author: Muhammad Hassan Siddiqui
Author-email: mhassan.eeng@gmail.com
Classifier: Framework :: FastAPI
Classifier: License :: OSI Approved :: MIT License
Classifier: Operating System :: OS Independent
Classifier: Programming Language :: Python :: 2
Classifier: Programming Language :: Python :: 2.7
Classifier: Programming Language :: Python :: 3
Classifier: Programming Language :: Python :: 3.4
Classifier: Programming Language :: Python :: 3.5
Classifier: Programming Language :: Python :: 3.6
Classifier: Programming Language :: Python :: 3.7
Classifier: Programming Language :: Python :: 3.8
Classifier: Programming Language :: Python :: 3.9
Classifier: Programming Language :: Python :: 3.10
Classifier: Programming Language :: Python :: 3.11
Classifier: Programming Language :: Python :: 3.12
Classifier: Typing :: Typed
Requires-Dist: click (>=8.0,<9.0)
Project-URL: Repository, https://github.com/mhsiddiqui/cmd-manager
